<?xml version="1.0" encoding="utf-8"?>
<openerp>
  <data noupdate="1">

        <record id="stock.seq_picking_in" model="ir.sequence">
            <field name="name">Picking IN</field>
            <field name="code">stock.picking.in</field>
            <field name="prefix">IN/</field>
            <field name="padding">5</field>
            <field name="company_id" eval="False"/>
            <field name="implementation">no_gap</field>
        </record>

        <record id="stock.seq_picking_out" model="ir.sequence">
            <field name="name">Picking OUT</field>
            <field name="code">stock.picking.out</field>
            <field name="prefix">OUT/</field>
            <field name="padding">5</field>
            <field name="company_id" eval="False"/>
            <field name="implementation">no_gap</field>
        </record>

        <record id="stock.seq_picking_internal" model="ir.sequence">
            <field name="name">Picking INT</field>
            <field name="code">stock.picking.internal</field>
            <field name="prefix">INT/</field>
            <field name="padding">5</field>
            <field name="company_id" eval="False"/>
            <field name="implementation">no_gap</field>
        </record>

        <record id="sale.seq_sale_order" model="ir.sequence">
            <field name="name">Sales Order</field>
            <field name="code">sale.order</field>
            <field name="prefix">SO</field>
            <field name="padding">3</field>
            <field name="company_id" eval="False"/>
            <field name="implementation">no_gap</field>
        </record>

        <record id="purchase.seq_purchase_order" model="ir.sequence">
            <field name="name">Purchase Order</field>
            <field name="code">purchase.order</field>
            <field name="prefix">PO</field>
            <field name="padding">5</field>
            <field name="company_id" eval="False"/>
            <field name="implementation">no_gap</field>
        </record>
    </data>
</openerp>

